{
  "id": "page",
  "label": "Page",
  "repeatable": true,
  "status": true,
  "json": {
    "Main": {
      "uid": {
        "type": "UID",
        "config": {
          "label": "Route",
          "placeholder": ""
        }
      },
      "navigation": {
        "type": "Select",
        "config": {
          "label": "Navigation",
          "placeholder": "",
          "options": [
            "Light",
            "Dark"
          ],
          "default_value": "Light"
        }
      },
      "slices": {
        "type": "Slices",
        "fieldset": "Slice Zone",
        "config": {
          "choices": {
            "accomplishments": {
              "type": "SharedSlice"
            },
            "clients": {
              "type": "SharedSlice"
            },
            "hero": {
              "type": "SharedSlice"
            },
            "image_slider": {
              "type": "SharedSlice"
            },
            "location": {
              "type": "SharedSlice"
            },
            "logo": {
              "type": "SharedSlice"
            },
            "projects": {
              "type": "SharedSlice"
            },
            "service": {
              "type": "SharedSlice"
            },
            "services": {
              "type": "SharedSlice"
            },
            "story": {
              "type": "SharedSlice"
            },
            "team": {
              "type": "SharedSlice"
            },
            "team_preview": {
              "type": "SharedSlice"
            },
            "collage": {
              "type": "SharedSlice"
            },
            "image": {
              "type": "SharedSlice"
            },
            "next_project": {
              "type": "SharedSlice"
            },
            "two_images": {
              "type": "SharedSlice"
            },
            "richtext": {
              "type": "SharedSlice"
            }
          }
        }
      }
    },
    "SEO": {
      "title_tag": {
        "type": "Text",
        "config": {
          "label": "Title Tag",
          "placeholder": ""
        }
      },
      "meta_title": {
        "type": "Text",
        "config": {
          "label": "Meta Title",
          "placeholder": ""
        }
      },
      "meta_description": {
        "type": "Text",
        "config": {
          "label": "Meta Description",
          "placeholder": ""
        }
      },
      "seo_meta_image": {
        "type": "Image",
        "config": {
          "label": "Meta Image",
          "constraint": {},
          "thumbnails": []
        }
      }
    }
  }
}