{
  "id": "homepage",
  "label": "Homepage",
  "repeatable": false,
  "status": true,
  "json": {
    "Main": {
      "slices": {
        "type": "Slices",
        "fieldset": "Slice Zone",
        "config": {
          "choices": {
            "accomplishments": {
              "type": "SharedSlice"
            },
            "clients": {
              "type": "SharedSlice"
            },
            "hero": {
              "type": "SharedSlice"
            },
            "image_slider": {
              "type": "SharedSlice"
            },
            "location": {
              "type": "SharedSlice"
            },
            "logo": {
              "type": "SharedSlice"
            },
            "service": {
              "type": "SharedSlice"
            },
            "projects": {
              "type": "SharedSlice"
            },
            "services": {
              "type": "SharedSlice"
            },
            "story": {
              "type": "SharedSlice"
            },
            "team": {
              "type": "SharedSlice"
            },
            "team_preview": {
              "type": "SharedSlice"
            },
            "video_single": {
              "type": "SharedSlice"
            }
          }
        }
      }
    },
    "SEO": {
      "title_tag": {
        "type": "Text",
        "config": {
          "label": "Title Tag",
          "placeholder": ""
        }
      },
      "meta_title": {
        "type": "Text",
        "config": {
          "label": "Meta Title",
          "placeholder": ""
        }
      },
      "meta_description": {
        "type": "Text",
        "config": {
          "label": "Meta Description",
          "placeholder": ""
        }
      },
      "seo_meta_image": {
        "type": "Image",
        "config": {
          "label": "Meta Image",
          "constraint": {},
          "thumbnails": []
        }
      }
    }
  }
}